{
  "manager_id": "CAAPX",
  "holdings": [
    {
      "symbol": "MAT",
      "company_name": "Mattel Inc.",
      "manager_id": "CAAPX",
      "shares": 1752125,
      "value": 34044000,
      "percentage": 4.1,
      "portfolio_percent": 4.1,
      "reported_price": 19.43,
      "current_price": 20.2,
      "price_change_percent": 0.0,
      "recent_activity": "Reduce 13.75%",
      "week_52_low": 13.95,
      "week_52_high": 22.07,
      "reporting_date": "",
      "reporting_quarter": "Q3 2025",
      "market_cap": 0.0,
      "pe_ratio": 0.0,
      "dividend_yield": 0.0,
      "price_to_book": 0.0,
      "sector": "",
      "industry": "",
      "data_quality": "Low"
    },
    {
      "symbol": "NTRS",
      "company_name": "Northern Trust Corp.",
      "manager_id": "CAAPX",
      "shares": 319358,
      "value": 31505000,
      "percentage": 3.79,
      "portfolio_percent": 3.79,
      "reported_price": 98.65,
      "current_price": 124.23,
      "price_change_percent": 0.0,
      "recent_activity": "Reduce 7.28%",
      "week_52_low": 78.41,
      "week_52_high": 133.0,
      "reporting_date": "",
      "reporting_quarter": "Q3 2025",
      "market_cap": 0.0,
      "pe_ratio": 0.0,
      "dividend_yield": 0.0,
      "price_to_book": 0.0,
      "sector": "",
      "industry": "",
      "data_quality": "Low"
    },
    {
      "symbol": "IPG",
      "company_name": "Interpublic Group",
      "manager_id": "CAAPX",
      "shares": 1060737,
      "value": 28810000,
      "percentage": 3.47,
      "portfolio_percent": 3.47,
      "reported_price": 27.16,
      "current_price": 26.54,
      "price_change_percent": 0.0,
      "recent_activity": "Add 7.62%",
      "week_52_low": 22.2,
      "week_52_high": 32.2,
      "reporting_date": "",
      "reporting_quarter": "Q3 2025",
      "market_cap": 0.0,
      "pe_ratio": 0.0,
      "dividend_yield": 0.0,
      "price_to_book": 0.0,
      "sector": "",
      "industry": "",
      "data_quality": "Low"
    },
    {
      "symbol": "GNRC",
      "company_name": "Generac Holdings Inc.",
      "manager_id": "CAAPX",
      "shares": 220287,
      "value": 27899000,
      "percentage": 3.36,
      "portfolio_percent": 3.36,
      "reported_price": 126.65,
      "current_price": 152.92,
      "price_change_percent": 0.0,
      "recent_activity": "Add 36.69%",
      "week_52_low": 99.5,
      "week_52_high": 195.94,
      "reporting_date": "",
      "reporting_quarter": "Q3 2025",
      "market_cap": 0.0,
      "pe_ratio": 0.0,
      "dividend_yield": 0.0,
      "price_to_book": 0.0,
      "sector": "",
      "industry": "",
      "data_quality": "Low"
    },
    {
      "symbol": "FAF",
      "company_name": "First Amer'n Corp.",
      "manager_id": "CAAPX",
      "shares": 387434,
      "value": 25427000,
      "percentage": 3.06,
      "portfolio_percent": 3.06,
      "reported_price": 65.63,
      "current_price": 57.62,
      "price_change_percent": 0.0,
      "recent_activity": "Reduce 10.73%",
      "week_52_low": 53.09,
      "week_52_high": 69.1,
      "reporting_date": "",
      "reporting_quarter": "Q3 2025",
      "market_cap": 0.0,
      "pe_ratio": 0.0,
      "dividend_yield": 0.0,
      "price_to_book": 0.0,
      "sector": "",
      "industry": "",
      "data_quality": "Low"
    },
    {
      "symbol": "SCHW",
      "company_name": "Charles Schwab Corp.",
      "manager_id": "CAAPX",
      "shares": 313313,
      "value": 24526000,
      "percentage": 2.95,
      "portfolio_percent": 2.95,
      "reported_price": 78.28,
      "current_price": 95.15,
      "price_change_percent": 0.0,
      "recent_activity": "Reduce 6.66%",
      "week_52_low": 60.3,
      "week_52_high": 97.5,
      "reporting_date": "",
      "reporting_quarter": "Q3 2025",
      "market_cap": 0.0,
      "pe_ratio": 0.0,
      "dividend_yield": 0.0,
      "price_to_book": 0.0,
      "sector": "",
      "industry": "",
      "data_quality": "Low"
    },
    {
      "symbol": "MIDD",
      "company_name": "Middleby Corp.",
      "manager_id": "CAAPX",
      "shares": 159153,
      "value": 24188000,
      "percentage": 2.91,
      "portfolio_percent": 2.91,
      "reported_price": 151.98,
      "current_price": 149.57,
      "price_change_percent": 0.0,
      "recent_activity": "Reduce 7.02%",
      "week_52_low": 121.7,
      "week_52_high": 182.73,
      "reporting_date": "",
      "reporting_quarter": "Q3 2025",
      "market_cap": 0.0,
      "pe_ratio": 0.0,
      "dividend_yield": 0.0,
      "price_to_book": 0.0,
      "sector": "",
      "industry": "",
      "data_quality": "Low"
    },
    {
      "symbol": "KMX",
      "company_name": "CarMax Inc.",
      "manager_id": "CAAPX",
      "shares": 308191,
      "value": 24014000,
      "percentage": 2.89,
      "portfolio_percent": 2.89,
      "reported_price": 77.92,
      "current_price": 62.83,
      "price_change_percent": 0.0,
      "recent_activity": "Reduce 12.70%",
      "week_52_low": 61.34,
      "week_52_high": 91.25,
      "reporting_date": "",
      "reporting_quarter": "Q3 2025",
      "market_cap": 0.0,
      "pe_ratio": 0.0,
      "dividend_yield": 0.0,
      "price_to_book": 0.0,
      "sector": "",
      "industry": "",
      "data_quality": "Low"
    },
    {
      "symbol": "LH",
      "company_name": "Labcorp Holdings Inc.",
      "manager_id": "CAAPX",
      "shares": 100026,
      "value": 23280000,
      "percentage": 2.8,
      "portfolio_percent": 2.8,
      "reported_price": 232.74,
      "current_price": 250.51,
      "price_change_percent": 0.0,
      "recent_activity": "Reduce 14.70%",
      "week_52_low": 205.54,
      "week_52_high": 265.72,
      "reporting_date": "",
      "reporting_quarter": "Q3 2025",
      "market_cap": 0.0,
      "pe_ratio": 0.0,
      "dividend_yield": 0.0,
      "price_to_book": 0.0,
      "sector": "",
      "industry": "",
      "data_quality": "Low"
    },
    {
      "symbol": "SJM",
      "company_name": "J.M. Smucker Co",
      "manager_id": "CAAPX",
      "shares": 195921,
      "value": 23199000,
      "percentage": 2.79,
      "portfolio_percent": 2.79,
      "reported_price": 118.41,
      "current_price": 109.12,
      "price_change_percent": 0.0,
      "recent_activity": "Add 11.32%",
      "week_52_low": 93.3,
      "week_52_high": 122.94,
      "reporting_date": "",
      "reporting_quarter": "Q3 2025",
      "market_cap": 0.0,
      "pe_ratio": 0.0,
      "dividend_yield": 0.0,
      "price_to_book": 0.0,
      "sector": "",
      "industry": "",
      "data_quality": "Low"
    },
    {
      "symbol": "CG",
      "company_name": "Carlyle Group",
      "manager_id": "CAAPX",
      "shares": 522026,
      "value": 22755000,
      "percentage": 2.74,
      "portfolio_percent": 2.74,
      "reported_price": 43.59,
      "current_price": 61.05,
      "price_change_percent": 0.0,
      "recent_activity": "Reduce 6.50%",
      "week_52_low": 32.78,
      "week_52_high": 61.1,
      "reporting_date": "",
      "reporting_quarter": "Q3 2025",
      "market_cap": 0.0,
      "pe_ratio": 0.0,
      "dividend_yield": 0.0,
      "price_to_book": 0.0,
      "sector": "",
      "industry": "",
      "data_quality": "Low"
    },
    {
      "symbol": "LAZ",
      "company_name": "Lazard Inc.",
      "manager_id": "CAAPX",
      "shares": 512587,
      "value": 22195000,
      "percentage": 2.67,
      "portfolio_percent": 2.67,
      "reported_price": 43.3,
      "current_price": 54.97,
      "price_change_percent": 0.0,
      "recent_activity": "Reduce 3.45%",
      "week_52_low": 31.58,
      "week_52_high": 59.33,
      "reporting_date": "",
      "reporting_quarter": "Q3 2025",
      "market_cap": 0.0,
      "pe_ratio": 0.0,
      "dividend_yield": 0.0,
      "price_to_book": 0.0,
      "sector": "",
      "industry": "",
      "data_quality": "Low"
    },
    {
      "symbol": "JLL",
      "company_name": "Jones Lang Lasalle Inc.",
      "manager_id": "CAAPX",
      "shares": 88369,
      "value": 21908000,
      "percentage": 2.64,
      "portfolio_percent": 2.64,
      "reported_price": 247.91,
      "current_price": 260.8,
      "price_change_percent": 0.0,
      "recent_activity": "Reduce 6.67%",
      "week_52_low": 194.36,
      "week_52_high": 288.5,
      "reporting_date": "",
      "reporting_quarter": "Q3 2025",
      "market_cap": 0.0,
      "pe_ratio": 0.0,
      "dividend_yield": 0.0,
      "price_to_book": 0.0,
      "sector": "",
      "industry": "",
      "data_quality": "Low"
    },
    {
      "symbol": "BOKF",
      "company_name": "BOK Financial Corp.",
      "manager_id": "CAAPX",
      "shares": 206231,
      "value": 21479000,
      "percentage": 2.58,
      "portfolio_percent": 2.58,
      "reported_price": 104.15,
      "current_price": 107.25,
      "price_change_percent": 0.0,
      "recent_activity": "",
      "week_52_low": 84.58,
      "week_52_high": 120.26,
      "reporting_date": "",
      "reporting_quarter": "Q3 2025",
      "market_cap": 0.0,
      "pe_ratio": 0.0,
      "dividend_yield": 0.0,
      "price_to_book": 0.0,
      "sector": "",
      "industry": "",
      "data_quality": "Low"
    },
    {
      "symbol": "BIO",
      "company_name": "Bio-Rad Laboratories Inc.",
      "manager_id": "CAAPX",
      "shares": 87404,
      "value": 21288000,
      "percentage": 2.56,
      "portfolio_percent": 2.56,
      "reported_price": 243.56,
      "current_price": 257.07,
      "price_change_percent": 0.0,
      "recent_activity": "Add 14.83%",
      "week_52_low": 211.43,
      "week_52_high": 387.99,
      "reporting_date": "",
      "reporting_quarter": "Q3 2025",
      "market_cap": 0.0,
      "pe_ratio": 0.0,
      "dividend_yield": 0.0,
      "price_to_book": 0.0,
      "sector": "",
      "industry": "",
      "data_quality": "Low"
    },
    {
      "symbol": "CLB",
      "company_name": "Core Laboratories Inc.",
      "manager_id": "CAAPX",
      "shares": 1411250,
      "value": 21155000,
      "percentage": 2.54,
      "portfolio_percent": 2.54,
      "reported_price": 14.99,
      "current_price": 12.62,
      "price_change_percent": 0.0,
      "recent_activity": "Add 2.10%",
      "week_52_low": 10.14,
      "week_52_high": 25.07,
      "reporting_date": "",
      "reporting_quarter": "Q3 2025",
      "market_cap": 0.0,
      "pe_ratio": 0.0,
      "dividend_yield": 0.0,
      "price_to_book": 0.0,
      "sector": "",
      "industry": "",
      "data_quality": "Low"
    },
    {
      "symbol": "SLB",
      "company_name": "Schlumberger Ltd.",
      "manager_id": "CAAPX",
      "shares": 505033,
      "value": 21110000,
      "percentage": 2.54,
      "portfolio_percent": 2.54,
      "reported_price": 41.8,
      "current_price": 35.14,
      "price_change_percent": 0.0,
      "recent_activity": "Buy",
      "week_52_low": 30.85,
      "week_52_high": 47.94,
      "reporting_date": "",
      "reporting_quarter": "Q3 2025",
      "market_cap": 0.0,
      "pe_ratio": 0.0,
      "dividend_yield": 0.0,
      "price_to_book": 0.0,
      "sector": "",
      "industry": "",
      "data_quality": "Low"
    },
    {
      "symbol": "CRL",
      "company_name": "Charles River Labs",
      "manager_id": "CAAPX",
      "shares": 138571,
      "value": 20858000,
      "percentage": 2.51,
      "portfolio_percent": 2.51,
      "reported_price": 150.52,
      "current_price": 167.95,
      "price_change_percent": 0.0,
      "recent_activity": "Reduce 6.97%",
      "week_52_low": 91.86,
      "week_52_high": 254.15,
      "reporting_date": "",
      "reporting_quarter": "Q3 2025",
      "market_cap": 0.0,
      "pe_ratio": 0.0,
      "dividend_yield": 0.0,
      "price_to_book": 0.0,
      "sector": "",
      "industry": "",
      "data_quality": "Low"
    },
    {
      "symbol": "NVST",
      "company_name": "Envista Holdings Corp.",
      "manager_id": "CAAPX",
      "shares": 1193594,
      "value": 20601000,
      "percentage": 2.48,
      "portfolio_percent": 2.48,
      "reported_price": 17.26,
      "current_price": 20.75,
      "price_change_percent": 0.0,
      "recent_activity": "Reduce 7.31%",
      "week_52_low": 14.22,
      "week_52_high": 23.0,
      "reporting_date": "",
      "reporting_quarter": "Q3 2025",
      "market_cap": 0.0,
      "pe_ratio": 0.0,
      "dividend_yield": 0.0,
      "price_to_book": 0.0,
      "sector": "",
      "industry": "",
      "data_quality": "Low"
    },
    {
      "symbol": "MSGS",
      "company_name": "Madison Square Garden Sports Corp.",
      "manager_id": "CAAPX",
      "shares": 105474,
      "value": 20538000,
      "percentage": 2.47,
      "portfolio_percent": 2.47,
      "reported_price": 194.72,
      "current_price": 205.0,
      "price_change_percent": 0.0,
      "recent_activity": "Reduce 7.82%",
      "week_52_low": 173.26,
      "week_52_high": 237.99,
      "reporting_date": "",
      "reporting_quarter": "Q3 2025",
      "market_cap": 0.0,
      "pe_ratio": 0.0,
      "dividend_yield": 0.0,
      "price_to_book": 0.0,
      "sector": "",
      "industry": "",
      "data_quality": "Low"
    },
    {
      "symbol": "MSGE",
      "company_name": "Madison Square Garden Entertainment Corp.",
      "manager_id": "CAAPX",
      "shares": 623080,
      "value": 20400000,
      "percentage": 2.45,
      "portfolio_percent": 2.45,
      "reported_price": 32.74,
      "current_price": 40.86,
      "price_change_percent": 0.0,
      "recent_activity": "Add 0.06%",
      "week_52_low": 28.29,
      "week_52_high": 44.14,
      "reporting_date": "",
      "reporting_quarter": "Q3 2025",
      "market_cap": 0.0,
      "pe_ratio": 0.0,
      "dividend_yield": 0.0,
      "price_to_book": 0.0,
      "sector": "",
      "industry": "",
      "data_quality": "Low"
    },
    {
      "symbol": "KEYS",
      "company_name": "Keysight Technologies Inc.",
      "manager_id": "CAAPX",
      "shares": 133723,
      "value": 20028000,
      "percentage": 2.41,
      "portfolio_percent": 2.41,
      "reported_price": 149.77,
      "current_price": 167.99,
      "price_change_percent": 0.0,
      "recent_activity": "Reduce 4.12%",
      "week_52_low": 119.72,
      "week_52_high": 186.2,
      "reporting_date": "",
      "reporting_quarter": "Q3 2025",
      "market_cap": 0.0,
      "pe_ratio": 0.0,
      "dividend_yield": 0.0,
      "price_to_book": 0.0,
      "sector": "",
      "industry": "",
      "data_quality": "Low"
    },
    {
      "symbol": "GNTX",
      "company_name": "Gentex Corp.",
      "manager_id": "CAAPX",
      "shares": 818327,
      "value": 19067000,
      "percentage": 2.29,
      "portfolio_percent": 2.29,
      "reported_price": 23.3,
      "current_price": 23.86,
      "price_change_percent": 0.0,
      "recent_activity": "Add 20.44%",
      "week_52_low": 20.17,
      "week_52_high": 32.78,
      "reporting_date": "",
      "reporting_quarter": "Q3 2025",
      "market_cap": 0.0,
      "pe_ratio": 0.0,
      "dividend_yield": 0.0,
      "price_to_book": 0.0,
      "sector": "",
      "industry": "",
      "data_quality": "Low"
    },
    {
      "symbol": "SWK",
      "company_name": "Stanley Black & Decker Inc.",
      "manager_id": "CAAPX",
      "shares": 245677,
      "value": 18888000,
      "percentage": 2.27,
      "portfolio_percent": 2.27,
      "reported_price": 76.88,
      "current_price": 74.09,
      "price_change_percent": 0.0,
      "recent_activity": "Reduce 4.07%",
      "week_52_low": 53.22,
      "week_52_high": 107.4,
      "reporting_date": "",
      "reporting_quarter": "Q3 2025",
      "market_cap": 0.0,
      "pe_ratio": 0.0,
      "dividend_yield": 0.0,
      "price_to_book": 0.0,
      "sector": "",
      "industry": "",
      "data_quality": "Low"
    },
    {
      "symbol": "ZBH",
      "company_name": "Zimmer Biomet Holdings",
      "manager_id": "CAAPX",
      "shares": 164532,
      "value": 18622000,
      "percentage": 2.24,
      "portfolio_percent": 2.24,
      "reported_price": 113.18,
      "current_price": 97.33,
      "price_change_percent": 0.0,
      "recent_activity": "",
      "week_52_low": 88.99,
      "week_52_high": 115.64,
      "reporting_date": "",
      "reporting_quarter": "Q3 2025",
      "market_cap": 0.0,
      "pe_ratio": 0.0,
      "dividend_yield": 0.0,
      "price_to_book": 0.0,
      "sector": "",
      "industry": "",
      "data_quality": "Low"
    },
    {
      "symbol": "KN",
      "company_name": "Knowles Corp.",
      "manager_id": "CAAPX",
      "shares": 1220569,
      "value": 18553000,
      "percentage": 2.23,
      "portfolio_percent": 2.23,
      "reported_price": 15.2,
      "current_price": 19.0,
      "price_change_percent": 0.0,
      "recent_activity": "Add 2.23%",
      "week_52_low": 12.19,
      "week_52_high": 20.86,
      "reporting_date": "",
      "reporting_quarter": "Q3 2025",
      "market_cap": 0.0,
      "pe_ratio": 0.0,
      "dividend_yield": 0.0,
      "price_to_book": 0.0,
      "sector": "",
      "industry": "",
      "data_quality": "Low"
    },
    {
      "symbol": "AXTA",
      "company_name": "Axalta Coating Systems Ltd.",
      "manager_id": "CAAPX",
      "shares": 556761,
      "value": 18468000,
      "percentage": 2.22,
      "portfolio_percent": 2.22,
      "reported_price": 33.17,
      "current_price": 30.04,
      "price_change_percent": 0.0,
      "recent_activity": "Reduce 9.29%",
      "week_52_low": 27.7,
      "week_52_high": 41.66,
      "reporting_date": "",
      "reporting_quarter": "Q3 2025",
      "market_cap": 0.0,
      "pe_ratio": 0.0,
      "dividend_yield": 0.0,
      "price_to_book": 0.0,
      "sector": "",
      "industry": "",
      "data_quality": "Low"
    },
    {
      "symbol": "CBRE",
      "company_name": "CBRE Group",
      "manager_id": "CAAPX",
      "shares": 140194,
      "value": 18335000,
      "percentage": 2.21,
      "portfolio_percent": 2.21,
      "reported_price": 130.78,
      "current_price": 144.63,
      "price_change_percent": 0.0,
      "recent_activity": "Reduce 27.65%",
      "week_52_low": 97.85,
      "week_52_high": 147.75,
      "reporting_date": "",
      "reporting_quarter": "Q3 2025",
      "market_cap": 0.0,
      "pe_ratio": 0.0,
      "dividend_yield": 0.0,
      "price_to_book": 0.0,
      "sector": "",
      "industry": "",
      "data_quality": "Low"
    },
    {
      "symbol": "TAP",
      "company_name": "Molson Coors Beverage Co.",
      "manager_id": "CAAPX",
      "shares": 300304,
      "value": 18280000,
      "percentage": 2.2,
      "portfolio_percent": 2.2,
      "reported_price": 60.87,
      "current_price": 52.08,
      "price_change_percent": 0.0,
      "recent_activity": "",
      "week_52_low": 46.94,
      "week_52_high": 64.07,
      "reporting_date": "",
      "reporting_quarter": "Q3 2025",
      "market_cap": 0.0,
      "pe_ratio": 0.0,
      "dividend_yield": 0.0,
      "price_to_book": 0.0,
      "sector": "",
      "industry": "",
      "data_quality": "Low"
    },
    {
      "symbol": "KKR",
      "company_name": "KKR & Co. L.P.",
      "manager_id": "CAAPX",
      "shares": 155962,
      "value": 18031000,
      "percentage": 2.17,
      "portfolio_percent": 2.17,
      "reported_price": 115.61,
      "current_price": 148.26,
      "price_change_percent": 0.0,
      "recent_activity": "Add 17.46%",
      "week_52_low": 86.02,
      "week_52_high": 169.92,
      "reporting_date": "",
      "reporting_quarter": "Q3 2025",
      "market_cap": 0.0,
      "pe_ratio": 0.0,
      "dividend_yield": 0.0,
      "price_to_book": 0.0,
      "sector": "",
      "industry": "",
      "data_quality": "Low"
    },
    {
      "symbol": "SPHR",
      "company_name": "Sphere Entertainment Co.",
      "manager_id": "CAAPX",
      "shares": 526479,
      "value": 17226000,
      "percentage": 2.07,
      "portfolio_percent": 2.07,
      "reported_price": 32.72,
      "current_price": 47.0,
      "price_change_percent": 0.0,
      "recent_activity": "Add 23.14%",
      "week_52_low": 23.89,
      "week_52_high": 50.88,
      "reporting_date": "",
      "reporting_quarter": "Q3 2025",
      "market_cap": 0.0,
      "pe_ratio": 0.0,
      "dividend_yield": 0.0,
      "price_to_book": 0.0,
      "sector": "",
      "industry": "",
      "data_quality": "Low"
    },
    {
      "symbol": "NCLH",
      "company_name": "Norwegian Cruise Line Hlgs Ltd.",
      "manager_id": "CAAPX",
      "shares": 902583,
      "value": 17113000,
      "percentage": 2.06,
      "portfolio_percent": 2.06,
      "reported_price": 18.96,
      "current_price": 24.32,
      "price_change_percent": 0.0,
      "recent_activity": "Buy",
      "week_52_low": 14.21,
      "week_52_high": 29.29,
      "reporting_date": "",
      "reporting_quarter": "Q3 2025",
      "market_cap": 0.0,
      "pe_ratio": 0.0,
      "dividend_yield": 0.0,
      "price_to_book": 0.0,
      "sector": "",
      "industry": "",
      "data_quality": "Low"
    },
    {
      "symbol": "ADT",
      "company_name": "ADT Inc.",
      "manager_id": "CAAPX",
      "shares": 2094400,
      "value": 17048000,
      "percentage": 2.05,
      "portfolio_percent": 2.05,
      "reported_price": 8.14,
      "current_price": 8.43,
      "price_change_percent": 0.0,
      "recent_activity": "Reduce 18.80%",
      "week_52_low": 6.34,
      "week_52_high": 8.66,
      "reporting_date": "",
      "reporting_quarter": "Q3 2025",
      "market_cap": 0.0,
      "pe_ratio": 0.0,
      "dividend_yield": 0.0,
      "price_to_book": 0.0,
      "sector": "",
      "industry": "",
      "data_quality": "Low"
    },
    {
      "symbol": "KMT",
      "company_name": "Kennametal Inc.",
      "manager_id": "CAAPX",
      "shares": 794239,
      "value": 16917000,
      "percentage": 2.04,
      "portfolio_percent": 2.04,
      "reported_price": 21.3,
      "current_price": 25.7,
      "price_change_percent": 0.0,
      "recent_activity": "Reduce 8.36%",
      "week_52_low": 17.14,
      "week_52_high": 31.39,
      "reporting_date": "",
      "reporting_quarter": "Q3 2025",
      "market_cap": 0.0,
      "pe_ratio": 0.0,
      "dividend_yield": 0.0,
      "price_to_book": 0.0,
      "sector": "",
      "industry": "",
      "data_quality": "Low"
    },
    {
      "symbol": "REZI",
      "company_name": "Resideo Technologies Inc.",
      "manager_id": "CAAPX",
      "shares": 792097,
      "value": 14020000,
      "percentage": 1.69,
      "portfolio_percent": 1.69,
      "reported_price": 17.7,
      "current_price": 24.68,
      "price_change_percent": 0.0,
      "recent_activity": "Add 7.99%",
      "week_52_low": 14.18,
      "week_52_high": 28.28,
      "reporting_date": "",
      "reporting_quarter": "Q3 2025",
      "market_cap": 0.0,
      "pe_ratio": 0.0,
      "dividend_yield": 0.0,
      "price_to_book": 0.0,
      "sector": "",
      "industry": "",
      "data_quality": "Low"
    },
    {
      "symbol": "AFL",
      "company_name": "AFLAC Inc.",
      "manager_id": "CAAPX",
      "shares": 115387,
      "value": 12830000,
      "percentage": 1.54,
      "portfolio_percent": 1.54,
      "reported_price": 111.19,
      "current_price": 102.89,
      "price_change_percent": 0.0,
      "recent_activity": "Reduce 35.28%",
      "week_52_low": 91.83,
      "week_52_high": 114.16,
      "reporting_date": "",
      "reporting_quarter": "Q3 2025",
      "market_cap": 0.0,
      "pe_ratio": 0.0,
      "dividend_yield": 0.0,
      "price_to_book": 0.0,
      "sector": "",
      "industry": "",
      "data_quality": "Low"
    },
    {
      "symbol": "LFUS",
      "company_name": "Littelfuse Inc.",
      "manager_id": "CAAPX",
      "shares": 65248,
      "value": 12837000,
      "percentage": 1.54,
      "portfolio_percent": 1.54,
      "reported_price": 196.74,
      "current_price": 232.48,
      "price_change_percent": 0.0,
      "recent_activity": "",
      "week_52_low": 141.63,
      "week_52_high": 273.08,
      "reporting_date": "",
      "reporting_quarter": "Q3 2025",
      "market_cap": 0.0,
      "pe_ratio": 0.0,
      "dividend_yield": 0.0,
      "price_to_book": 0.0,
      "sector": "",
      "industry": "",
      "data_quality": "Low"
    },
    {
      "symbol": "MANU",
      "company_name": "Manchester United plc",
      "manager_id": "CAAPX",
      "shares": 932978,
      "value": 12213000,
      "percentage": 1.47,
      "portfolio_percent": 1.47,
      "reported_price": 13.09,
      "current_price": 18.17,
      "price_change_percent": 0.0,
      "recent_activity": "",
      "week_52_low": 12.05,
      "week_52_high": 19.65,
      "reporting_date": "",
      "reporting_quarter": "Q3 2025",
      "market_cap": 0.0,
      "pe_ratio": 0.0,
      "dividend_yield": 0.0,
      "price_to_book": 0.0,
      "sector": "",
      "industry": "",
      "data_quality": "Low"
    },
    {
      "symbol": "PARA",
      "company_name": "Paramount Global CL B",
      "manager_id": "CAAPX",
      "shares": 905261,
      "value": 10827000,
      "percentage": 1.3,
      "portfolio_percent": 1.3,
      "reported_price": 11.96,
      "current_price": 13.2,
      "price_change_percent": 0.0,
      "recent_activity": "Add 27.26%",
      "week_52_low": 9.78,
      "week_52_high": 13.29,
      "reporting_date": "",
      "reporting_quarter": "Q3 2025",
      "market_cap": 0.0,
      "pe_ratio": 0.0,
      "dividend_yield": 0.0,
      "price_to_book": 0.0,
      "sector": "",
      "industry": "",
      "data_quality": "Low"
    },
    {
      "symbol": "OSW",
      "company_name": "OneSpaWorld Holdings Ltd",
      "manager_id": "CAAPX",
      "shares": 625213,
      "value": 10497000,
      "percentage": 1.26,
      "portfolio_percent": 1.26,
      "reported_price": 16.79,
      "current_price": 22.11,
      "price_change_percent": 0.0,
      "recent_activity": "Buy",
      "week_52_low": 14.18,
      "week_52_high": 22.91,
      "reporting_date": "",
      "reporting_quarter": "Q3 2025",
      "market_cap": 0.0,
      "pe_ratio": 0.0,
      "dividend_yield": 0.0,
      "price_to_book": 0.0,
      "sector": "",
      "industry": "",
      "data_quality": "Low"
    },
    {
      "symbol": "NVT",
      "company_name": "nVent Electric plc",
      "manager_id": "CAAPX",
      "shares": 196365,
      "value": 10293000,
      "percentage": 1.24,
      "portfolio_percent": 1.24,
      "reported_price": 52.42,
      "current_price": 76.63,
      "price_change_percent": 0.0,
      "recent_activity": "",
      "week_52_low": 41.44,
      "week_52_high": 80.47,
      "reporting_date": "",
      "reporting_quarter": "Q3 2025",
      "market_cap": 0.0,
      "pe_ratio": 0.0,
      "dividend_yield": 0.0,
      "price_to_book": 0.0,
      "sector": "",
      "industry": "",
      "data_quality": "Low"
    },
    {
      "symbol": "BWA",
      "company_name": "BorgWarner Inc.",
      "manager_id": "CAAPX",
      "shares": 350020,
      "value": 10028000,
      "percentage": 1.21,
      "portfolio_percent": 1.21,
      "reported_price": 28.65,
      "current_price": 36.53,
      "price_change_percent": 0.0,
      "recent_activity": "Reduce 34.52%",
      "week_52_low": 24.32,
      "week_52_high": 36.91,
      "reporting_date": "",
      "reporting_quarter": "Q3 2025",
      "market_cap": 0.0,
      "pe_ratio": 0.0,
      "dividend_yield": 0.0,
      "price_to_book": 0.0,
      "sector": "",
      "industry": "",
      "data_quality": "Low"
    }
  ],
  "timestamp": "2025-08-01T06:07:05.329952",
  "scraped_date": "2025-08-01"
}