{
  "manager_id": "SA",
  "holdings": [
    {
      "symbol": "BRK.B",
      "company_name": "Berkshire Hathaway CL B",
      "manager_id": "SA",
      "shares": 239349,
      "value": 127472000,
      "percentage": 20.55,
      "portfolio_percent": 20.55,
      "reported_price": 532.58,
      "current_price": 482.63,
      "price_change_percent": 0.0,
      "recent_activity": "Add 0.54%",
      "week_52_low": 406.11,
      "week_52_high": 542.07,
      "reporting_date": "Apr 26, 2025",
      "reporting_quarter": "Q3 2025",
      "market_cap": 0.0,
      "pe_ratio": 0.0,
      "dividend_yield": 0.0,
      "price_to_book": 0.0,
      "sector": "",
      "industry": "",
      "data_quality": "Low"
    },
    {
      "symbol": "BRK.A",
      "company_name": "Berkshire Hathaway CL A",
      "manager_id": "SA",
      "shares": 116,
      "value": 92619000,
      "percentage": 14.93,
      "portfolio_percent": 14.93,
      "reported_price": 798439.66,
      "current_price": 723120.0,
      "price_change_percent": 0.0,
      "recent_activity": "Reduce 3.33%",
      "week_52_low": 609578.55,
      "week_52_high": 812855.0,
      "reporting_date": "Apr 26, 2025",
      "reporting_quarter": "Q3 2025",
      "market_cap": 0.0,
      "pe_ratio": 0.0,
      "dividend_yield": 0.0,
      "price_to_book": 0.0,
      "sector": "",
      "industry": "",
      "data_quality": "Low"
    },
    {
      "symbol": "DG",
      "company_name": "Dollar General",
      "manager_id": "SA",
      "shares": 907179,
      "value": 79768000,
      "percentage": 12.86,
      "portfolio_percent": 12.86,
      "reported_price": 87.93,
      "current_price": 109.24,
      "price_change_percent": 0.0,
      "recent_activity": "Add 48.35%",
      "week_52_low": 65.67,
      "week_52_high": 123.68,
      "reporting_date": "Apr 26, 2025",
      "reporting_quarter": "Q3 2025",
      "market_cap": 0.0,
      "pe_ratio": 0.0,
      "dividend_yield": 0.0,
      "price_to_book": 0.0,
      "sector": "",
      "industry": "",
      "data_quality": "Low"
    },
    {
      "symbol": "KGC",
      "company_name": "Kinross Gold Corp.",
      "manager_id": "SA",
      "shares": 4506646,
      "value": 56829000,
      "percentage": 9.16,
      "portfolio_percent": 9.16,
      "reported_price": 12.61,
      "current_price": 16.17,
      "price_change_percent": 0.0,
      "recent_activity": "Reduce 2.20%",
      "week_52_low": 7.75,
      "week_52_high": 16.52,
      "reporting_date": "Apr 26, 2025",
      "reporting_quarter": "Q3 2025",
      "market_cap": 0.0,
      "pe_ratio": 0.0,
      "dividend_yield": 0.0,
      "price_to_book": 0.0,
      "sector": "",
      "industry": "",
      "data_quality": "Low"
    },
    {
      "symbol": "DLTR",
      "company_name": "Dollar Tree Inc.",
      "manager_id": "SA",
      "shares": 493386,
      "value": 37038000,
      "percentage": 5.97,
      "portfolio_percent": 5.97,
      "reported_price": 75.07,
      "current_price": 114.92,
      "price_change_percent": 0.0,
      "recent_activity": "Reduce 37.05%",
      "week_52_low": 60.49,
      "week_52_high": 115.42,
      "reporting_date": "Apr 26, 2025",
      "reporting_quarter": "Q3 2025",
      "market_cap": 0.0,
      "pe_ratio": 0.0,
      "dividend_yield": 0.0,
      "price_to_book": 0.0,
      "sector": "",
      "industry": "",
      "data_quality": "Low"
    },
    {
      "symbol": "NEM",
      "company_name": "Newmont Corp.",
      "manager_id": "SA",
      "shares": 662556,
      "value": 31988000,
      "percentage": 5.16,
      "portfolio_percent": 5.16,
      "reported_price": 48.28,
      "current_price": 61.42,
      "price_change_percent": 0.0,
      "recent_activity": "Add 0.87%",
      "week_52_low": 36.47,
      "week_52_high": 62.56,
      "reporting_date": "Apr 26, 2025",
      "reporting_quarter": "Q3 2025",
      "market_cap": 0.0,
      "pe_ratio": 0.0,
      "dividend_yield": 0.0,
      "price_to_book": 0.0,
      "sector": "",
      "industry": "",
      "data_quality": "Low"
    },
    {
      "symbol": "VLO",
      "company_name": "Valero Energy",
      "manager_id": "SA",
      "shares": 190494,
      "value": 25159000,
      "percentage": 4.06,
      "portfolio_percent": 4.06,
      "reported_price": 132.07,
      "current_price": 147.54,
      "price_change_percent": 0.0,
      "recent_activity": "Add 0.78%",
      "week_52_low": 98.17,
      "week_52_high": 162.69,
      "reporting_date": "Apr 26, 2025",
      "reporting_quarter": "Q3 2025",
      "market_cap": 0.0,
      "pe_ratio": 0.0,
      "dividend_yield": 0.0,
      "price_to_book": 0.0,
      "sector": "",
      "industry": "",
      "data_quality": "Low"
    },
    {
      "symbol": "SBUX",
      "company_name": "Starbucks Corp.",
      "manager_id": "SA",
      "shares": 231702,
      "value": 22728000,
      "percentage": 3.66,
      "portfolio_percent": 3.66,
      "reported_price": 98.09,
      "current_price": 95.92,
      "price_change_percent": 0.0,
      "recent_activity": "Reduce 0.87%",
      "week_52_low": 70.96,
      "week_52_high": 116.64,
      "reporting_date": "Apr 26, 2025",
      "reporting_quarter": "Q3 2025",
      "market_cap": 0.0,
      "pe_ratio": 0.0,
      "dividend_yield": 0.0,
      "price_to_book": 0.0,
      "sector": "",
      "industry": "",
      "data_quality": "Low"
    },
    {
      "symbol": "PARA",
      "company_name": "Paramount Global CL B",
      "manager_id": "SA",
      "shares": 1632655,
      "value": 19527000,
      "percentage": 3.15,
      "portfolio_percent": 3.15,
      "reported_price": 11.96,
      "current_price": 13.2,
      "price_change_percent": 0.0,
      "recent_activity": "Add 38.35%",
      "week_52_low": 9.78,
      "week_52_high": 13.29,
      "reporting_date": "Apr 26, 2025",
      "reporting_quarter": "Q3 2025",
      "market_cap": 0.0,
      "pe_ratio": 0.0,
      "dividend_yield": 0.0,
      "price_to_book": 0.0,
      "sector": "",
      "industry": "",
      "data_quality": "Low"
    },
    {
      "symbol": "OLN",
      "company_name": "Olin Corp.",
      "manager_id": "SA",
      "shares": 702466,
      "value": 17028000,
      "percentage": 2.75,
      "portfolio_percent": 2.75,
      "reported_price": 24.24,
      "current_price": 21.84,
      "price_change_percent": 0.0,
      "recent_activity": "Add 19.98%",
      "week_52_low": 17.5,
      "week_52_high": 48.53,
      "reporting_date": "Apr 26, 2025",
      "reporting_quarter": "Q3 2025",
      "market_cap": 0.0,
      "pe_ratio": 0.0,
      "dividend_yield": 0.0,
      "price_to_book": 0.0,
      "sector": "",
      "industry": "",
      "data_quality": "Low"
    },
    {
      "symbol": "ALK",
      "company_name": "Alaska Air Group",
      "manager_id": "SA",
      "shares": 344834,
      "value": 16973000,
      "percentage": 2.74,
      "portfolio_percent": 2.74,
      "reported_price": 49.22,
      "current_price": 53.88,
      "price_change_percent": 0.0,
      "recent_activity": "Reduce 1.50%",
      "week_52_low": 32.62,
      "week_52_high": 78.08,
      "reporting_date": "Apr 26, 2025",
      "reporting_quarter": "Q3 2025",
      "market_cap": 0.0,
      "pe_ratio": 0.0,
      "dividend_yield": 0.0,
      "price_to_book": 0.0,
      "sector": "",
      "industry": "",
      "data_quality": "Low"
    },
    {
      "symbol": "DIS",
      "company_name": "Walt Disney Co.",
      "manager_id": "SA",
      "shares": 139801,
      "value": 13798000,
      "percentage": 2.22,
      "portfolio_percent": 2.22,
      "reported_price": 98.7,
      "current_price": 122.94,
      "price_change_percent": 0.0,
      "recent_activity": "Reduce 0.19%",
      "week_52_low": 79.76,
      "week_52_high": 124.69,
      "reporting_date": "Apr 26, 2025",
      "reporting_quarter": "Q3 2025",
      "market_cap": 0.0,
      "pe_ratio": 0.0,
      "dividend_yield": 0.0,
      "price_to_book": 0.0,
      "sector": "",
      "industry": "",
      "data_quality": "Low"
    },
    {
      "symbol": "EQNR",
      "company_name": "Equinor ASA",
      "manager_id": "SA",
      "shares": 490166,
      "value": 12965000,
      "percentage": 2.09,
      "portfolio_percent": 2.09,
      "reported_price": 26.45,
      "current_price": 25.95,
      "price_change_percent": 0.0,
      "recent_activity": "Add 0.01%",
      "week_52_low": 20.55,
      "week_52_high": 28.27,
      "reporting_date": "Apr 26, 2025",
      "reporting_quarter": "Q3 2025",
      "market_cap": 0.0,
      "pe_ratio": 0.0,
      "dividend_yield": 0.0,
      "price_to_book": 0.0,
      "sector": "",
      "industry": "",
      "data_quality": "Low"
    },
    {
      "symbol": "CMI",
      "company_name": "Cummins Inc.",
      "manager_id": "SA",
      "shares": 40039,
      "value": 12550000,
      "percentage": 2.02,
      "portfolio_percent": 2.02,
      "reported_price": 313.44,
      "current_price": 361.98,
      "price_change_percent": 0.0,
      "recent_activity": "Reduce 1.03%",
      "week_52_low": 258.55,
      "week_52_high": 383.88,
      "reporting_date": "Apr 26, 2025",
      "reporting_quarter": "Q3 2025",
      "market_cap": 0.0,
      "pe_ratio": 0.0,
      "dividend_yield": 0.0,
      "price_to_book": 0.0,
      "sector": "",
      "industry": "",
      "data_quality": "Low"
    },
    {
      "symbol": "DINO",
      "company_name": "HF Sinclair Corp.",
      "manager_id": "SA",
      "shares": 299281,
      "value": 9840000,
      "percentage": 1.59,
      "portfolio_percent": 1.59,
      "reported_price": 32.88,
      "current_price": 45.74,
      "price_change_percent": 0.0,
      "recent_activity": "Add 2.18%",
      "week_52_low": 24.33,
      "week_52_high": 50.19,
      "reporting_date": "Apr 26, 2025",
      "reporting_quarter": "Q3 2025",
      "market_cap": 0.0,
      "pe_ratio": 0.0,
      "dividend_yield": 0.0,
      "price_to_book": 0.0,
      "sector": "",
      "industry": "",
      "data_quality": "Low"
    },
    {
      "symbol": "XOM",
      "company_name": "Exxon Mobil Corp.",
      "manager_id": "SA",
      "shares": 56272,
      "value": 6692000,
      "percentage": 1.08,
      "portfolio_percent": 1.08,
      "reported_price": 118.92,
      "current_price": 109.93,
      "price_change_percent": 0.0,
      "recent_activity": "Reduce 0.28%",
      "week_52_low": 96.91,
      "week_52_high": 123.07,
      "reporting_date": "Apr 26, 2025",
      "reporting_quarter": "Q3 2025",
      "market_cap": 0.0,
      "pe_ratio": 0.0,
      "dividend_yield": 0.0,
      "price_to_book": 0.0,
      "sector": "",
      "industry": "",
      "data_quality": "Low"
    },
    {
      "symbol": "FIVE",
      "company_name": "Five Below Inc.",
      "manager_id": "SA",
      "shares": 78664,
      "value": 5894000,
      "percentage": 0.95,
      "portfolio_percent": 0.95,
      "reported_price": 74.93,
      "current_price": 139.37,
      "price_change_percent": 0.0,
      "recent_activity": "Add 3.02%",
      "week_52_low": 52.38,
      "week_52_high": 142.13,
      "reporting_date": "Apr 26, 2025",
      "reporting_quarter": "Q3 2025",
      "market_cap": 0.0,
      "pe_ratio": 0.0,
      "dividend_yield": 0.0,
      "price_to_book": 0.0,
      "sector": "",
      "industry": "",
      "data_quality": "Low"
    },
    {
      "symbol": "TRV",
      "company_name": "Travelers Companies Inc.",
      "manager_id": "SA",
      "shares": 20155,
      "value": 5330000,
      "percentage": 0.86,
      "portfolio_percent": 0.86,
      "reported_price": 264.45,
      "current_price": 264.74,
      "price_change_percent": 0.0,
      "recent_activity": "",
      "week_52_low": 202.52,
      "week_52_high": 276.69,
      "reporting_date": "Apr 26, 2025",
      "reporting_quarter": "Q3 2025",
      "market_cap": 0.0,
      "pe_ratio": 0.0,
      "dividend_yield": 0.0,
      "price_to_book": 0.0,
      "sector": "",
      "industry": "",
      "data_quality": "Low"
    },
    {
      "symbol": "COST",
      "company_name": "Costco Co.",
      "manager_id": "SA",
      "shares": 4245,
      "value": 4015000,
      "percentage": 0.65,
      "portfolio_percent": 0.65,
      "reported_price": 945.82,
      "current_price": 941.19,
      "price_change_percent": 0.0,
      "recent_activity": "Reduce 2.41%",
      "week_52_low": 790.04,
      "week_52_high": 1076.83,
      "reporting_date": "Apr 26, 2025",
      "reporting_quarter": "Q3 2025",
      "market_cap": 0.0,
      "pe_ratio": 0.0,
      "dividend_yield": 0.0,
      "price_to_book": 0.0,
      "sector": "",
      "industry": "",
      "data_quality": "Low"
    },
    {
      "symbol": "MRK",
      "company_name": "Merck & Co.",
      "manager_id": "SA",
      "shares": 44443,
      "value": 3989000,
      "percentage": 0.64,
      "portfolio_percent": 0.64,
      "reported_price": 89.76,
      "current_price": 83.98,
      "price_change_percent": 0.0,
      "recent_activity": "",
      "week_52_low": 72.58,
      "week_52_high": 124.53,
      "reporting_date": "Apr 26, 2025",
      "reporting_quarter": "Q3 2025",
      "market_cap": 0.0,
      "pe_ratio": 0.0,
      "dividend_yield": 0.0,
      "price_to_book": 0.0,
      "sector": "",
      "industry": "",
      "data_quality": "Low"
    },
    {
      "symbol": "NXPI",
      "company_name": "NXP Semiconductors NV",
      "manager_id": "SA",
      "shares": 13558,
      "value": 2577000,
      "percentage": 0.42,
      "portfolio_percent": 0.42,
      "reported_price": 190.07,
      "current_price": 224.71,
      "price_change_percent": 0.0,
      "recent_activity": "Reduce 0.95%",
      "week_52_low": 147.4,
      "week_52_high": 259.69,
      "reporting_date": "Apr 26, 2025",
      "reporting_quarter": "Q3 2025",
      "market_cap": 0.0,
      "pe_ratio": 0.0,
      "dividend_yield": 0.0,
      "price_to_book": 0.0,
      "sector": "",
      "industry": "",
      "data_quality": "Low"
    },
    {
      "symbol": "NKE",
      "company_name": "NIKE Inc.",
      "manager_id": "SA",
      "shares": 36550,
      "value": 2320000,
      "percentage": 0.37,
      "portfolio_percent": 0.37,
      "reported_price": 63.47,
      "current_price": 76.75,
      "price_change_percent": 0.0,
      "recent_activity": "Add 2.67%",
      "week_52_low": 51.93,
      "week_52_high": 89.11,
      "reporting_date": "Apr 26, 2025",
      "reporting_quarter": "Q3 2025",
      "market_cap": 0.0,
      "pe_ratio": 0.0,
      "dividend_yield": 0.0,
      "price_to_book": 0.0,
      "sector": "",
      "industry": "",
      "data_quality": "Low"
    },
    {
      "symbol": "GE",
      "company_name": "GE Aerospace",
      "manager_id": "SA",
      "shares": 9842,
      "value": 1970000,
      "percentage": 0.32,
      "portfolio_percent": 0.32,
      "reported_price": 200.16,
      "current_price": 263.18,
      "price_change_percent": 0.0,
      "recent_activity": "",
      "week_52_low": 149.24,
      "week_52_high": 272.8,
      "reporting_date": "Apr 26, 2025",
      "reporting_quarter": "Q3 2025",
      "market_cap": 0.0,
      "pe_ratio": 0.0,
      "dividend_yield": 0.0,
      "price_to_book": 0.0,
      "sector": "",
      "industry": "",
      "data_quality": "Low"
    },
    {
      "symbol": "KO",
      "company_name": "Coca Cola Co.",
      "manager_id": "SA",
      "shares": 22000,
      "value": 1576000,
      "percentage": 0.25,
      "portfolio_percent": 0.25,
      "reported_price": 71.64,
      "current_price": 69.16,
      "price_change_percent": 0.0,
      "recent_activity": "Reduce 1.23%",
      "week_52_low": 59.75,
      "week_52_high": 73.85,
      "reporting_date": "Apr 26, 2025",
      "reporting_quarter": "Q3 2025",
      "market_cap": 0.0,
      "pe_ratio": 0.0,
      "dividend_yield": 0.0,
      "price_to_book": 0.0,
      "sector": "",
      "industry": "",
      "data_quality": "Low"
    },
    {
      "symbol": "AXP",
      "company_name": "American Express",
      "manager_id": "SA",
      "shares": 4432,
      "value": 1192000,
      "percentage": 0.19,
      "portfolio_percent": 0.19,
      "reported_price": 268.95,
      "current_price": 308.66,
      "price_change_percent": 0.0,
      "recent_activity": "",
      "week_52_low": 219.65,
      "week_52_high": 329.14,
      "reporting_date": "Apr 26, 2025",
      "reporting_quarter": "Q3 2025",
      "market_cap": 0.0,
      "pe_ratio": 0.0,
      "dividend_yield": 0.0,
      "price_to_book": 0.0,
      "sector": "",
      "industry": "",
      "data_quality": "Low"
    },
    {
      "symbol": "GEV",
      "company_name": "Ge Vernova Inc",
      "manager_id": "SA",
      "shares": 3738,
      "value": 1141000,
      "percentage": 0.18,
      "portfolio_percent": 0.18,
      "reported_price": 305.24,
      "current_price": 629.03,
      "price_change_percent": 0.0,
      "recent_activity": "Reduce 9.67%",
      "week_52_low": 149.72,
      "week_52_high": 633.72,
      "reporting_date": "Apr 26, 2025",
      "reporting_quarter": "Q3 2025",
      "market_cap": 0.0,
      "pe_ratio": 0.0,
      "dividend_yield": 0.0,
      "price_to_book": 0.0,
      "sector": "",
      "industry": "",
      "data_quality": "Low"
    },
    {
      "symbol": "CVX",
      "company_name": "Chevron Corp.",
      "manager_id": "SA",
      "shares": 6163,
      "value": 1031000,
      "percentage": 0.17,
      "portfolio_percent": 0.17,
      "reported_price": 167.29,
      "current_price": 153.12,
      "price_change_percent": 0.0,
      "recent_activity": "",
      "week_52_low": 130.45,
      "week_52_high": 166.93,
      "reporting_date": "Apr 26, 2025",
      "reporting_quarter": "Q3 2025",
      "market_cap": 0.0,
      "pe_ratio": 0.0,
      "dividend_yield": 0.0,
      "price_to_book": 0.0,
      "sector": "",
      "industry": "",
      "data_quality": "Low"
    },
    {
      "symbol": "SGOV",
      "company_name": "Ishares 0 3 Month Treasury B",
      "manager_id": "SA",
      "shares": 10600,
      "value": 1067000,
      "percentage": 0.17,
      "portfolio_percent": 0.17,
      "reported_price": 100.66,
      "current_price": 100.63,
      "price_change_percent": 0.0,
      "recent_activity": "Buy",
      "week_52_low": 96.16,
      "week_52_high": 100.63,
      "reporting_date": "Apr 26, 2025",
      "reporting_quarter": "Q3 2025",
      "market_cap": 0.0,
      "pe_ratio": 0.0,
      "dividend_yield": 0.0,
      "price_to_book": 0.0,
      "sector": "",
      "industry": "",
      "data_quality": "Low"
    },
    {
      "symbol": "SMHI",
      "company_name": "SEACOR Marine Holdings Inc.",
      "manager_id": "SA",
      "shares": 211480,
      "value": 1070000,
      "percentage": 0.17,
      "portfolio_percent": 0.17,
      "reported_price": 5.06,
      "current_price": 5.65,
      "price_change_percent": 0.0,
      "recent_activity": "",
      "week_52_low": 3.63,
      "week_52_high": 14.52,
      "reporting_date": "Apr 26, 2025",
      "reporting_quarter": "Q3 2025",
      "market_cap": 0.0,
      "pe_ratio": 0.0,
      "dividend_yield": 0.0,
      "price_to_book": 0.0,
      "sector": "",
      "industry": "",
      "data_quality": "Low"
    },
    {
      "symbol": "GLDM",
      "company_name": "SPDR Gold Minishares Trust",
      "manager_id": "SA",
      "shares": 16219,
      "value": 1004000,
      "percentage": 0.16,
      "portfolio_percent": 0.16,
      "reported_price": 61.9,
      "current_price": 67.13,
      "price_change_percent": 0.0,
      "recent_activity": "Add 12.91%",
      "week_52_low": 46.63,
      "week_52_high": 68.26,
      "reporting_date": "Apr 26, 2025",
      "reporting_quarter": "Q3 2025",
      "market_cap": 0.0,
      "pe_ratio": 0.0,
      "dividend_yield": 0.0,
      "price_to_book": 0.0,
      "sector": "",
      "industry": "",
      "data_quality": "Low"
    },
    {
      "symbol": "AAPL",
      "company_name": "Apple Inc.",
      "manager_id": "SA",
      "shares": 4140,
      "value": 920000,
      "percentage": 0.15,
      "portfolio_percent": 0.15,
      "reported_price": 222.22,
      "current_price": 214.15,
      "price_change_percent": 0.0,
      "recent_activity": "",
      "week_52_low": 168.99,
      "week_52_high": 259.47,
      "reporting_date": "Apr 26, 2025",
      "reporting_quarter": "Q3 2025",
      "market_cap": 0.0,
      "pe_ratio": 0.0,
      "dividend_yield": 0.0,
      "price_to_book": 0.0,
      "sector": "",
      "industry": "",
      "data_quality": "Low"
    },
    {
      "symbol": "OVV",
      "company_name": "Ovintiv Inc.",
      "manager_id": "SA",
      "shares": 16487,
      "value": 706000,
      "percentage": 0.11,
      "portfolio_percent": 0.11,
      "reported_price": 42.82,
      "current_price": 39.47,
      "price_change_percent": 0.0,
      "recent_activity": "",
      "week_52_low": 29.58,
      "week_52_high": 46.91,
      "reporting_date": "Apr 26, 2025",
      "reporting_quarter": "Q3 2025",
      "market_cap": 0.0,
      "pe_ratio": 0.0,
      "dividend_yield": 0.0,
      "price_to_book": 0.0,
      "sector": "",
      "industry": "",
      "data_quality": "Low"
    },
    {
      "symbol": "PHYS",
      "company_name": "Sprott Physical Gold Trust",
      "manager_id": "SA",
      "shares": 23869,
      "value": 574000,
      "percentage": 0.09,
      "portfolio_percent": 0.09,
      "reported_price": 24.05,
      "current_price": 25.99,
      "price_change_percent": 0.0,
      "recent_activity": "",
      "week_52_low": 18.23,
      "week_52_high": 26.42,
      "reporting_date": "Apr 26, 2025",
      "reporting_quarter": "Q3 2025",
      "market_cap": 0.0,
      "pe_ratio": 0.0,
      "dividend_yield": 0.0,
      "price_to_book": 0.0,
      "sector": "",
      "industry": "",
      "data_quality": "Low"
    },
    {
      "symbol": "GEHC",
      "company_name": "GE HealthCare Technologies Inc.",
      "manager_id": "SA",
      "shares": 4581,
      "value": 370000,
      "percentage": 0.06,
      "portfolio_percent": 0.06,
      "reported_price": 80.77,
      "current_price": 77.25,
      "price_change_percent": 0.0,
      "recent_activity": "",
      "week_52_low": 57.62,
      "week_52_high": 94.75,
      "reporting_date": "Apr 26, 2025",
      "reporting_quarter": "Q3 2025",
      "market_cap": 0.0,
      "pe_ratio": 0.0,
      "dividend_yield": 0.0,
      "price_to_book": 0.0,
      "sector": "",
      "industry": "",
      "data_quality": "Low"
    },
    {
      "symbol": "SHEL",
      "company_name": "Shell plc",
      "manager_id": "SA",
      "shares": 4968,
      "value": 364000,
      "percentage": 0.06,
      "portfolio_percent": 0.06,
      "reported_price": 73.27,
      "current_price": 72.76,
      "price_change_percent": 0.0,
      "recent_activity": "",
      "week_52_low": 57.92,
      "week_52_high": 73.39,
      "reporting_date": "Apr 26, 2025",
      "reporting_quarter": "Q3 2025",
      "market_cap": 0.0,
      "pe_ratio": 0.0,
      "dividend_yield": 0.0,
      "price_to_book": 0.0,
      "sector": "",
      "industry": "",
      "data_quality": "Low"
    },
    {
      "symbol": "SYF",
      "company_name": "Synchrony Financial",
      "manager_id": "SA",
      "shares": 4437,
      "value": 235000,
      "percentage": 0.04,
      "portfolio_percent": 0.04,
      "reported_price": 52.96,
      "current_price": 72.08,
      "price_change_percent": 0.0,
      "recent_activity": "",
      "week_52_low": 40.32,
      "week_52_high": 72.73,
      "reporting_date": "Apr 26, 2025",
      "reporting_quarter": "Q3 2025",
      "market_cap": 0.0,
      "pe_ratio": 0.0,
      "dividend_yield": 0.0,
      "price_to_book": 0.0,
      "sector": "",
      "industry": "",
      "data_quality": "Low"
    }
  ],
  "timestamp": "2025-08-11T04:38:17.284379",
  "scraped_date": "2025-08-11"
}