{
  "manager_id": "HH",
  "activities": [
    {
      "symbol": "PDD",
      "manager_id": "HH",
      "action": "Add 7.27%",
      "date": "Q1 2025",
      "percentage_change": 0.0,
      "action_type": "Add",
      "shares": 525200,
      "portfolio_percentage": 0.52,
      "company_name": "Pinduoduo Inc."
    },
    {
      "symbol": "OXY",
      "manager_id": "HH",
      "action": "Add 1.83%",
      "date": "Q1 2025",
      "percentage_change": 0.0,
      "action_type": "Add",
      "shares": 249100,
      "portfolio_percentage": 0.1,
      "company_name": "Occidental Petroleum"
    },
    {
      "symbol": "MSFT",
      "manager_id": "HH",
      "action": "Buy",
      "date": "Q1 2025",
      "percentage_change": 0.0,
      "action_type": "Buy",
      "shares": 299200,
      "portfolio_percentage": 0.94,
      "company_name": "Microsoft Corp."
    },
    {
      "symbol": "NVDA",
      "manager_id": "HH",
      "action": "Buy",
      "date": "Q1 2025",
      "percentage_change": 0.0,
      "action_type": "Buy",
      "shares": 645100,
      "portfolio_percentage": 0.58,
      "company_name": "NVIDIA Corp."
    },
    {
      "symbol": "TSM",
      "manager_id": "HH",
      "action": "Buy",
      "date": "Q1 2025",
      "percentage_change": 0.0,
      "action_type": "Buy",
      "shares": 271792,
      "portfolio_percentage": 0.38,
      "company_name": "Taiwan Semiconductor S.A."
    },
    {
      "symbol": "DIS",
      "manager_id": "HH",
      "action": "Reduce 3.08%",
      "date": "Q1 2025",
      "percentage_change": 0.0,
      "action_type": "Reduce",
      "shares": 23000,
      "portfolio_percentage": 0.02,
      "company_name": "Walt Disney Co."
    },
    {
      "symbol": "BRK.B",
      "manager_id": "HH",
      "action": "Reduce 6.62%",
      "date": "Q1 2025",
      "percentage_change": 0.0,
      "action_type": "Reduce",
      "shares": 239800,
      "portfolio_percentage": 1.06,
      "company_name": "Berkshire Hathaway CL B"
    },
    {
      "symbol": "AAPL",
      "manager_id": "HH",
      "action": "Reduce 16.25%",
      "date": "Q1 2025",
      "percentage_change": 0.0,
      "action_type": "Reduce",
      "shares": 6640396,
      "portfolio_percentage": 12.29,
      "company_name": "Apple Inc."
    },
    {
      "symbol": "BABA",
      "manager_id": "HH",
      "action": "Reduce 26.94%",
      "date": "Q1 2025",
      "percentage_change": 0.0,
      "action_type": "Reduce",
      "shares": 1468700,
      "portfolio_percentage": 1.62,
      "company_name": "Alibaba Group Holdings"
    },
    {
      "symbol": "MRNA",
      "manager_id": "HH",
      "action": "Reduce 49.08%",
      "date": "Q1 2025",
      "percentage_change": 0.0,
      "action_type": "Reduce",
      "shares": 80000,
      "portfolio_percentage": 0.02,
      "company_name": "Moderna Inc."
    },
    {
      "symbol": "GOOG",
      "manager_id": "HH",
      "action": "Reduce 70.51%",
      "date": "Q1 2025",
      "percentage_change": 0.0,
      "action_type": "Reduce",
      "shares": 2655900,
      "portfolio_percentage": 3.47,
      "company_name": "Alphabet Inc. CL C"
    },
    {
      "symbol": "PDD",
      "manager_id": "HH",
      "action": "Add 84.99%",
      "date": "Q4 2024",
      "percentage_change": 0.0,
      "action_type": "Add",
      "shares": 3321100,
      "portfolio_percentage": 2.22,
      "company_name": "Pinduoduo Inc."
    },
    {
      "symbol": "MRNA",
      "manager_id": "HH",
      "action": "Add 66.84%",
      "date": "Q4 2024",
      "percentage_change": 0.0,
      "action_type": "Add",
      "shares": 65300,
      "portfolio_percentage": 0.02,
      "company_name": "Moderna Inc."
    },
    {
      "symbol": "OXY",
      "manager_id": "HH",
      "action": "Add 47.20%",
      "date": "Q4 2024",
      "percentage_change": 0.0,
      "action_type": "Add",
      "shares": 4353300,
      "portfolio_percentage": 1.48,
      "company_name": "Occidental Petroleum"
    },
    {
      "symbol": "BABA",
      "manager_id": "HH",
      "action": "Add 0.13%",
      "date": "Q4 2024",
      "percentage_change": 0.0,
      "action_type": "Add",
      "shares": 7100,
      "portfolio_percentage": 0.0,
      "company_name": "Alibaba Group Holdings"
    },
    {
      "symbol": "DIS",
      "manager_id": "HH",
      "action": "Reduce 0.33%",
      "date": "Q4 2024",
      "percentage_change": 0.0,
      "action_type": "Reduce",
      "shares": 2500,
      "portfolio_percentage": 0.0,
      "company_name": "Walt Disney Co."
    },
    {
      "symbol": "BRK.B",
      "manager_id": "HH",
      "action": "Reduce 4.26%",
      "date": "Q4 2024",
      "percentage_change": 0.0,
      "action_type": "Reduce",
      "shares": 161000,
      "portfolio_percentage": 0.5,
      "company_name": "Berkshire Hathaway CL B"
    },
    {
      "symbol": "AAPL",
      "manager_id": "HH",
      "action": "Reduce 22.56%",
      "date": "Q4 2024",
      "percentage_change": 0.0,
      "action_type": "Reduce",
      "shares": 11904578,
      "portfolio_percentage": 20.54,
      "company_name": "Apple Inc."
    },
    {
      "symbol": "GOOG",
      "manager_id": "HH",
      "action": "Reduce 25.66%",
      "date": "Q4 2024",
      "percentage_change": 0.0,
      "action_type": "Reduce",
      "shares": 1299800,
      "portfolio_percentage": 1.7,
      "company_name": "Alphabet Inc. CL C"
    },
    {
      "symbol": "PDD",
      "manager_id": "HH",
      "action": "Add 3693.79%",
      "date": "Q3 2024",
      "percentage_change": 0.0,
      "action_type": "Add",
      "shares": 3804600,
      "portfolio_percentage": 3.1,
      "company_name": "Pinduoduo Inc."
    },
    {
      "symbol": "OXY",
      "manager_id": "HH",
      "action": "Add 497.74%",
      "date": "Q3 2024",
      "percentage_change": 0.0,
      "action_type": "Add",
      "shares": 7680598,
      "portfolio_percentage": 2.39,
      "company_name": "Occidental Petroleum"
    },
    {
      "symbol": "GOOG",
      "manager_id": "HH",
      "action": "Add 0.80%",
      "date": "Q3 2024",
      "percentage_change": 0.0,
      "action_type": "Add",
      "shares": 40300,
      "portfolio_percentage": 0.04,
      "company_name": "Alphabet Inc. CL C"
    },
    {
      "symbol": "BRK.B",
      "manager_id": "HH",
      "action": "Reduce 3.00%",
      "date": "Q3 2024",
      "percentage_change": 0.0,
      "action_type": "Reduce",
      "shares": 117000,
      "portfolio_percentage": 0.33,
      "company_name": "Berkshire Hathaway CL B"
    },
    {
      "symbol": "BABA",
      "manager_id": "HH",
      "action": "Reduce 13.69%",
      "date": "Q3 2024",
      "percentage_change": 0.0,
      "action_type": "Reduce",
      "shares": 863100,
      "portfolio_percentage": 0.55,
      "company_name": "Alibaba Group Holdings"
    },
    {
      "symbol": "AAPL",
      "manager_id": "HH",
      "action": "Reduce 17.45%",
      "date": "Q3 2024",
      "percentage_change": 0.0,
      "action_type": "Reduce",
      "shares": 11155100,
      "portfolio_percentage": 15.71,
      "company_name": "Apple Inc."
    },
    {
      "symbol": "MRNA",
      "manager_id": "HH",
      "action": "Reduce 30.56%",
      "date": "Q3 2024",
      "percentage_change": 0.0,
      "action_type": "Reduce",
      "shares": 43000,
      "portfolio_percentage": 0.02,
      "company_name": "Moderna Inc."
    },
    {
      "symbol": "BAC",
      "manager_id": "HH",
      "action": "Sell 100.00%",
      "date": "Q3 2024",
      "percentage_change": 0.0,
      "action_type": "Sell",
      "shares": 107900,
      "portfolio_percentage": 0.03,
      "company_name": "Bank of America Corp."
    },
    {
      "symbol": "OXY",
      "manager_id": "HH",
      "action": "Add 35.97%",
      "date": "Q2 2024",
      "percentage_change": 0.0,
      "action_type": "Add",
      "shares": 408200,
      "portfolio_percentage": 0.15,
      "company_name": "Occidental Petroleum"
    },
    {
      "symbol": "BABA",
      "manager_id": "HH",
      "action": "Add 7.90%",
      "date": "Q2 2024",
      "percentage_change": 0.0,
      "action_type": "Add",
      "shares": 461500,
      "portfolio_percentage": 0.2,
      "company_name": "Alibaba Group Holdings"
    },
    {
      "symbol": "DIS",
      "manager_id": "HH",
      "action": "Reduce 0.16%",
      "date": "Q2 2024",
      "percentage_change": 0.0,
      "action_type": "Reduce",
      "shares": 1200,
      "portfolio_percentage": 0.0,
      "company_name": "Walt Disney Co."
    },
    {
      "symbol": "AAPL",
      "manager_id": "HH",
      "action": "Reduce 1.02%",
      "date": "Q2 2024",
      "percentage_change": 0.0,
      "action_type": "Reduce",
      "shares": 658838,
      "portfolio_percentage": 0.83,
      "company_name": "Apple Inc."
    },
    {
      "symbol": "BAC",
      "manager_id": "HH",
      "action": "Reduce 1.64%",
      "date": "Q2 2024",
      "percentage_change": 0.0,
      "action_type": "Reduce",
      "shares": 1800,
      "portfolio_percentage": 0.0,
      "company_name": "Bank of America Corp."
    },
    {
      "symbol": "GOOG",
      "manager_id": "HH",
      "action": "Reduce 1.95%",
      "date": "Q2 2024",
      "percentage_change": 0.0,
      "action_type": "Reduce",
      "shares": 100000,
      "portfolio_percentage": 0.11,
      "company_name": "Alphabet Inc. CL C"
    },
    {
      "symbol": "BRK.B",
      "manager_id": "HH",
      "action": "Reduce 4.72%",
      "date": "Q2 2024",
      "percentage_change": 0.0,
      "action_type": "Reduce",
      "shares": 193100,
      "portfolio_percentage": 0.47,
      "company_name": "Berkshire Hathaway CL B"
    },
    {
      "symbol": "PDD",
      "manager_id": "HH",
      "action": "Reduce 6.36%",
      "date": "Q2 2024",
      "percentage_change": 0.0,
      "action_type": "Reduce",
      "shares": 7000,
      "portfolio_percentage": 0.01,
      "company_name": "Pinduoduo Inc."
    },
    {
      "symbol": "OXY",
      "manager_id": "HH",
      "action": "Add 157.87%",
      "date": "Q1 2024",
      "percentage_change": 0.0,
      "action_type": "Add",
      "shares": 694802,
      "portfolio_percentage": 0.32,
      "company_name": "Occidental Petroleum"
    },
    {
      "symbol": "BABA",
      "manager_id": "HH",
      "action": "Add 17.87%",
      "date": "Q1 2024",
      "percentage_change": 0.0,
      "action_type": "Add",
      "shares": 886100,
      "portfolio_percentage": 0.45,
      "company_name": "Alibaba Group Holdings"
    },
    {
      "symbol": "AAPL",
      "manager_id": "HH",
      "action": "Add 8.14%",
      "date": "Q1 2024",
      "percentage_change": 0.0,
      "action_type": "Add",
      "shares": 4860022,
      "portfolio_percentage": 5.87,
      "company_name": "Apple Inc."
    },
    {
      "symbol": "MRNA",
      "manager_id": "HH",
      "action": "Add 0.14%",
      "date": "Q1 2024",
      "percentage_change": 0.0,
      "action_type": "Add",
      "shares": 200,
      "portfolio_percentage": 0.0,
      "company_name": "Moderna Inc."
    },
    {
      "symbol": "PDD",
      "manager_id": "HH",
      "action": "Buy",
      "date": "Q1 2024",
      "percentage_change": 0.0,
      "action_type": "Buy",
      "shares": 110000,
      "portfolio_percentage": 0.09,
      "company_name": "Pinduoduo Inc."
    },
    {
      "symbol": "GOOG",
      "manager_id": "HH",
      "action": "Reduce 4.65%",
      "date": "Q1 2024",
      "percentage_change": 0.0,
      "action_type": "Reduce",
      "shares": 250100,
      "portfolio_percentage": 0.27,
      "company_name": "Alphabet Inc. CL C"
    },
    {
      "symbol": "BRK.B",
      "manager_id": "HH",
      "action": "Reduce 13.78%",
      "date": "Q1 2024",
      "percentage_change": 0.0,
      "action_type": "Reduce",
      "shares": 654102,
      "portfolio_percentage": 1.94,
      "company_name": "Berkshire Hathaway CL B"
    },
    {
      "symbol": "JOYY",
      "manager_id": "HH",
      "action": "Sell 100.00%",
      "date": "Q1 2024",
      "percentage_change": 0.0,
      "action_type": "Sell",
      "shares": 299900,
      "portfolio_percentage": 0.08,
      "company_name": "JOYY Inc."
    },
    {
      "symbol": "BABA",
      "manager_id": "HH",
      "action": "Add 63.11%",
      "date": "Q4 2023",
      "percentage_change": 0.0,
      "action_type": "Add",
      "shares": 1918730,
      "portfolio_percentage": 1.03,
      "company_name": "Alibaba Group Holdings"
    },
    {
      "symbol": "BAC",
      "manager_id": "HH",
      "action": "Add 52.15%",
      "date": "Q4 2023",
      "percentage_change": 0.0,
      "action_type": "Add",
      "shares": 37600,
      "portfolio_percentage": 0.01,
      "company_name": "Bank of America Corp."
    },
    {
      "symbol": "MRNA",
      "manager_id": "HH",
      "action": "Add 35.10%",
      "date": "Q4 2023",
      "percentage_change": 0.0,
      "action_type": "Add",
      "shares": 36500,
      "portfolio_percentage": 0.03,
      "company_name": "Moderna Inc."
    },
    {
      "symbol": "OXY",
      "manager_id": "HH",
      "action": "Buy",
      "date": "Q4 2023",
      "percentage_change": 0.0,
      "action_type": "Buy",
      "shares": 440100,
      "portfolio_percentage": 0.18,
      "company_name": "Occidental Petroleum"
    },
    {
      "symbol": "JOYY",
      "manager_id": "HH",
      "action": "Reduce 0.86%",
      "date": "Q4 2023",
      "percentage_change": 0.0,
      "action_type": "Reduce",
      "shares": 2600,
      "portfolio_percentage": 0.0,
      "company_name": "JOYY Inc."
    },
    {
      "symbol": "AAPL",
      "manager_id": "HH",
      "action": "Reduce 2.13%",
      "date": "Q4 2023",
      "percentage_change": 0.0,
      "action_type": "Reduce",
      "shares": 1296880,
      "portfolio_percentage": 1.73,
      "company_name": "Apple Inc."
    },
    {
      "symbol": "BRK.B",
      "manager_id": "HH",
      "action": "Reduce 5.19%",
      "date": "Q4 2023",
      "percentage_change": 0.0,
      "action_type": "Reduce",
      "shares": 259800,
      "portfolio_percentage": 0.64,
      "company_name": "Berkshire Hathaway CL B"
    },
    {
      "symbol": "DIS",
      "manager_id": "HH",
      "action": "Reduce 6.25%",
      "date": "Q4 2023",
      "percentage_change": 0.0,
      "action_type": "Reduce",
      "shares": 50000,
      "portfolio_percentage": 0.03,
      "company_name": "Walt Disney Co."
    },
    {
      "symbol": "PDD",
      "manager_id": "HH",
      "action": "Sell 100.00%",
      "date": "Q4 2023",
      "percentage_change": 0.0,
      "action_type": "Sell",
      "shares": 150000,
      "portfolio_percentage": 0.11,
      "company_name": "Pinduoduo Inc."
    },
    {
      "symbol": "AAPL",
      "manager_id": "HH",
      "action": "Add 0.64%",
      "date": "Q3 2023",
      "percentage_change": 0.0,
      "action_type": "Add",
      "shares": 385977,
      "portfolio_percentage": 0.5,
      "company_name": "Apple Inc."
    },
    {
      "symbol": "PDD",
      "manager_id": "HH",
      "action": "Buy",
      "date": "Q3 2023",
      "percentage_change": 0.0,
      "action_type": "Buy",
      "shares": 150000,
      "portfolio_percentage": 0.11,
      "company_name": "Pinduoduo Inc."
    },
    {
      "symbol": "BAC",
      "manager_id": "HH",
      "action": "Buy",
      "date": "Q3 2023",
      "percentage_change": 0.0,
      "action_type": "Buy",
      "shares": 72100,
      "portfolio_percentage": 0.01,
      "company_name": "Bank of America Corp."
    },
    {
      "symbol": "GOOG",
      "manager_id": "HH",
      "action": "Reduce 3.58%",
      "date": "Q3 2023",
      "percentage_change": 0.0,
      "action_type": "Reduce",
      "shares": 199800,
      "portfolio_percentage": 0.2,
      "company_name": "Alphabet Inc. CL C"
    },
    {
      "symbol": "BRK.B",
      "manager_id": "HH",
      "action": "Reduce 11.62%",
      "date": "Q3 2023",
      "percentage_change": 0.0,
      "action_type": "Reduce",
      "shares": 658363,
      "portfolio_percentage": 1.74,
      "company_name": "Berkshire Hathaway CL B"
    },
    {
      "symbol": "BABA",
      "manager_id": "HH",
      "action": "Reduce 13.32%",
      "date": "Q3 2023",
      "percentage_change": 0.0,
      "action_type": "Reduce",
      "shares": 467100,
      "portfolio_percentage": 0.31,
      "company_name": "Alibaba Group Holdings"
    },
    {
      "symbol": "DIS",
      "manager_id": "HH",
      "action": "Reduce 13.71%",
      "date": "Q3 2023",
      "percentage_change": 0.0,
      "action_type": "Reduce",
      "shares": 127100,
      "portfolio_percentage": 0.08,
      "company_name": "Walt Disney Co."
    },
    {
      "symbol": "MRNA",
      "manager_id": "HH",
      "action": "Reduce 25.71%",
      "date": "Q3 2023",
      "percentage_change": 0.0,
      "action_type": "Reduce",
      "shares": 36000,
      "portfolio_percentage": 0.03,
      "company_name": "Moderna Inc."
    },
    {
      "symbol": "OXY",
      "manager_id": "HH",
      "action": "Sell 100.00%",
      "date": "Q3 2023",
      "percentage_change": 0.0,
      "action_type": "Sell",
      "shares": 199900,
      "portfolio_percentage": 0.08,
      "company_name": "Occidental Petroleum"
    },
    {
      "symbol": "BABA",
      "manager_id": "HH",
      "action": "Add 12.53%",
      "date": "Q2 2023",
      "percentage_change": 0.0,
      "action_type": "Add",
      "shares": 390500,
      "portfolio_percentage": 0.22,
      "company_name": "Alibaba Group Holdings"
    },
    {
      "symbol": "BRK.B",
      "manager_id": "HH",
      "action": "Reduce 0.39%",
      "date": "Q2 2023",
      "percentage_change": 0.0,
      "action_type": "Reduce",
      "shares": 22000,
      "portfolio_percentage": 0.05,
      "company_name": "Berkshire Hathaway CL B"
    },
    {
      "symbol": "AAPL",
      "manager_id": "HH",
      "action": "Reduce 4.16%",
      "date": "Q2 2023",
      "percentage_change": 0.0,
      "action_type": "Reduce",
      "shares": 2628900,
      "portfolio_percentage": 3.45,
      "company_name": "Apple Inc."
    },
    {
      "symbol": "MRNA",
      "manager_id": "HH",
      "action": "Reduce 6.67%",
      "date": "Q2 2023",
      "percentage_change": 0.0,
      "action_type": "Reduce",
      "shares": 10000,
      "portfolio_percentage": 0.01,
      "company_name": "Moderna Inc."
    },
    {
      "symbol": "GOOG",
      "manager_id": "HH",
      "action": "Reduce 8.37%",
      "date": "Q2 2023",
      "percentage_change": 0.0,
      "action_type": "Reduce",
      "shares": 509500,
      "portfolio_percentage": 0.42,
      "company_name": "Alphabet Inc. CL C"
    },
    {
      "symbol": "OXY",
      "manager_id": "HH",
      "action": "Reduce 49.97%",
      "date": "Q2 2023",
      "percentage_change": 0.0,
      "action_type": "Reduce",
      "shares": 199700,
      "portfolio_percentage": 0.08,
      "company_name": "Occidental Petroleum"
    },
    {
      "symbol": "NTES",
      "manager_id": "HH",
      "action": "Sell 100.00%",
      "date": "Q2 2023",
      "percentage_change": 0.0,
      "action_type": "Sell",
      "shares": 100000,
      "portfolio_percentage": 0.07,
      "company_name": "NetEase.com Inc."
    },
    {
      "symbol": "AAPL",
      "manager_id": "HH",
      "action": "Add 3.32%",
      "date": "Q1 2023",
      "percentage_change": 0.0,
      "action_type": "Add",
      "shares": 2030174,
      "portfolio_percentage": 2.52,
      "company_name": "Apple Inc."
    },
    {
      "symbol": "GOOG",
      "manager_id": "HH",
      "action": "Add 1.84%",
      "date": "Q1 2023",
      "percentage_change": 0.0,
      "action_type": "Add",
      "shares": 110200,
      "portfolio_percentage": 0.09,
      "company_name": "Alphabet Inc. CL C"
    },
    {
      "symbol": "BABA",
      "manager_id": "HH",
      "action": "Add 0.41%",
      "date": "Q1 2023",
      "percentage_change": 0.0,
      "action_type": "Add",
      "shares": 12700,
      "portfolio_percentage": 0.01,
      "company_name": "Alibaba Group Holdings"
    },
    {
      "symbol": "OXY",
      "manager_id": "HH",
      "action": "Buy",
      "date": "Q1 2023",
      "percentage_change": 0.0,
      "action_type": "Buy",
      "shares": 399600,
      "portfolio_percentage": 0.19,
      "company_name": "Occidental Petroleum"
    },
    {
      "symbol": "NTES",
      "manager_id": "HH",
      "action": "Buy",
      "date": "Q1 2023",
      "percentage_change": 0.0,
      "action_type": "Buy",
      "shares": 100000,
      "portfolio_percentage": 0.07,
      "company_name": "NetEase.com Inc."
    },
    {
      "symbol": "MRNA",
      "manager_id": "HH",
      "action": "Reduce 6.25%",
      "date": "Q1 2023",
      "percentage_change": 0.0,
      "action_type": "Reduce",
      "shares": 10000,
      "portfolio_percentage": 0.01,
      "company_name": "Moderna Inc."
    },
    {
      "symbol": "BRK.B",
      "manager_id": "HH",
      "action": "Reduce 9.66%",
      "date": "Q1 2023",
      "percentage_change": 0.0,
      "action_type": "Reduce",
      "shares": 608000,
      "portfolio_percentage": 1.41,
      "company_name": "Berkshire Hathaway CL B"
    },
    {
      "symbol": "ZM",
      "manager_id": "HH",
      "action": "Sell 100.00%",
      "date": "Q1 2023",
      "percentage_change": 0.0,
      "action_type": "Sell",
      "shares": 179800,
      "portfolio_percentage": 0.11,
      "company_name": "Zoom Video Communications Inc."
    },
    {
      "symbol": "AAPL",
      "manager_id": "HH",
      "action": "Add 23.06%",
      "date": "Q4 2022",
      "percentage_change": 0.0,
      "action_type": "Add",
      "shares": 11474600,
      "portfolio_percentage": 13.76,
      "company_name": "Apple Inc."
    },
    {
      "symbol": "GOOG",
      "manager_id": "HH",
      "action": "Add 19.02%",
      "date": "Q4 2022",
      "percentage_change": 0.0,
      "action_type": "Add",
      "shares": 955000,
      "portfolio_percentage": 0.78,
      "company_name": "Alphabet Inc. CL C"
    },
    {
      "symbol": "BABA",
      "manager_id": "HH",
      "action": "Add 6.44%",
      "date": "Q4 2022",
      "percentage_change": 0.0,
      "action_type": "Add",
      "shares": 187900,
      "portfolio_percentage": 0.15,
      "company_name": "Alibaba Group Holdings"
    },
    {
      "symbol": "BRK.B",
      "manager_id": "HH",
      "action": "Reduce 3.00%",
      "date": "Q4 2022",
      "percentage_change": 0.0,
      "action_type": "Reduce",
      "shares": 194796,
      "portfolio_percentage": 0.56,
      "company_name": "Berkshire Hathaway CL B"
    },
    {
      "symbol": "ZM",
      "manager_id": "HH",
      "action": "Reduce 14.30%",
      "date": "Q4 2022",
      "percentage_change": 0.0,
      "action_type": "Reduce",
      "shares": 30000,
      "portfolio_percentage": 0.02,
      "company_name": "Zoom Video Communications Inc."
    }
  ],
  "timestamp": "2025-08-11T04:38:18.157679",
  "scraped_date": "2025-08-11"
}